miniflux_exporter/__init__.py
miniflux_exporter/__main__.py
miniflux_exporter/cli.py
miniflux_exporter/config.py
miniflux_exporter/exporter.py
miniflux_exporter/utils.py
miniflux_exporter-1.0.0.dist-info/licenses/LICENSE
miniflux_exporter-1.0.0.dist-info/METADATA
miniflux_exporter-1.0.0.dist-info/WHEEL
miniflux_exporter-1.0.0.dist-info/top_level.txt
miniflux_exporter-1.0.0.dist-info/RECORD
