Metadata-Version: 2.4
Name: miniflux-exporter
Version: 1.0.0
Summary: Export articles from Miniflux RSS reader to Markdown files
Home-page: https://github.com/bullishlee/miniflux-exporter
Author: Miniflux Exporter Contributors
Author-email: Your Name <your.email@example.com>
License: MIT
Project-URL: Homepage, https://github.com/bullishlee/miniflux-exporter
Project-URL: Repository, https://github.com/bullishlee/miniflux-exporter
Project-URL: Issues, https://github.com/bullishlee/miniflux-exporter/issues
Classifier: Development Status :: 4 - Beta
Classifier: Intended Audience :: Developers
Classifier: License :: OSI Approved :: MIT License
Classifier: Programming Language :: Python :: 3
Classifier: Programming Language :: Python :: 3.6
Classifier: Programming Language :: Python :: 3.7
Classifier: Programming Language :: Python :: 3.8
Classifier: Programming Language :: Python :: 3.9
Classifier: Programming Language :: Python :: 3.10
Classifier: Programming Language :: Python :: 3.11
Classifier: Programming Language :: Python :: 3.12
Requires-Python: >=3.6
License-File: LICENSE
Dynamic: author
Dynamic: home-page
Dynamic: license-file
Dynamic: requires-python
